agon.py
agon-0.1.0.post1.dist-info/WHEEL
agon-0.1.0.post1.dist-info/METADATA
agon-0.1.0.post1.dist-info/RECORD
